esper/__init__.py
esper/py.typed
esper-3.7.dist-info/licenses/LICENSE
esper-3.7.dist-info/WHEEL
esper-3.7.dist-info/METADATA
esper-3.7.dist-info/RECORD
