Metadata-Version: 2.4
Name: esper
Version: 3.7
Summary: esper is a lightweight Entity System (ECS) for Python, with a focus on performance
Author-email: Benjamin Moran <benmoran@protonmail.com>
Requires-Python: >=3.8
Classifier: License :: OSI Approved :: MIT License
License-File: LICENSE
Project-URL: Home, https://github.com/benmoran56/esper
